LICENSE.md
MANIFEST.in
README.md
setup.cfg
setup.py
binance/__init__.py
binance/__version__.py
binance/api.py
binance/error.py
binance/cm_futures/__init__.py
binance/cm_futures/account.py
binance/cm_futures/data_stream.py
binance/cm_futures/market.py
binance/cm_futures/portfolio_margin.py
binance/lib/__init__.py
binance/lib/authentication.py
binance/lib/utils.py
binance/um_futures/__init__.py
binance/um_futures/account.py
binance/um_futures/data_stream.py
binance/um_futures/market.py
binance/um_futures/portfolio_margin.py
binance/websocket/__init__.py
binance/websocket/binance_socket_manager.py
binance/websocket/websocket_client.py
binance/websocket/cm_futures/__init__.py
binance/websocket/cm_futures/websocket_client.py
binance/websocket/um_futures/__init__.py
binance/websocket/um_futures/websocket_client.py
bnb_futures_connector.egg-info/PKG-INFO
bnb_futures_connector.egg-info/SOURCES.txt
bnb_futures_connector.egg-info/dependency_links.txt
bnb_futures_connector.egg-info/requires.txt
bnb_futures_connector.egg-info/top_level.txt
requirements/common.txt