Metadata-Version: 2.1
Name: bnb-futures-connector
Version: 4.0.0
Summary: This is a lightweight library that works as a connector to Binance Futures public API.
Home-page: https://github.com/vonhathanh/binance-futures-connector-python
License: MIT
Keywords: Binance futures,Public API
Classifier: Intended Audience :: Developers
Classifier: Intended Audience :: Financial and Insurance Industry
Classifier: License :: OSI Approved :: MIT License
Classifier: Programming Language :: Python :: 3.8
Classifier: Programming Language :: Python :: 3.9
Classifier: Programming Language :: Python :: 3.10
Classifier: Programming Language :: Python :: 3.11
Requires-Python: >=3.7
License-File: LICENSE.md
Requires-Dist: requests>=2.25.1
Requires-Dist: websocket-client>=1.5.0
Requires-Dist: pycryptodome>=3.15.0
